winpwn/__init__.py
winpwn/context.py
winpwn/dbg.py
winpwn/misc.py
winpwn/var.py
winpwn/win.py
winpwn/winpwn.py
webpwn-0.0.1.dist-info/METADATA
webpwn-0.0.1.dist-info/WHEEL
webpwn-0.0.1.dist-info/top_level.txt
webpwn-0.0.1.dist-info/RECORD
